clautils/__init__.py
clautils/all.py
clautils-0.1.1.dist-info/METADATA
clautils-0.1.1.dist-info/WHEEL
clautils-0.1.1.dist-info/top_level.txt
clautils-0.1.1.dist-info/RECORD
